mat_ceng/__init__.py
mat_ceng/column.py
mat_ceng/column_area.py
mat_ceng/csi.py
mat_ceng/csi_interop/__init__.py
mat_ceng/csi_interop/etabs_api.py
mat_ceng/csi_interop/sap2000_api.py
mat_ceng/geotechnical/__init__.py
mat_ceng/geotechnical/foundation_design.py
mat_ceng/geotechnical/soil_mechanics.py
mat_ceng/mat_ceng.py
mat_ceng/py.typed
mat_ceng/structural/__init__.py
mat_ceng/structural/beam_analysis.py
mat_ceng/structural/slab_design.py
mat_ceng/surveying/__init__.py
mat_ceng/utils/__init__.py
mat_ceng/utils/geometry_helpers.py
mat_ceng-0.0.23.dist-info/WHEEL
mat_ceng-0.0.23.dist-info/METADATA
mat_ceng-0.0.23.dist-info/RECORD
