Metadata-Version: 2.3
Name: mat-ceng
Version: 0.0.23
Summary: useful tools for civil engineering that are needed regularly in the daily tasks for a civil engineer
Author: Mohamad Ali
Author-email: Mohamad Ali <mohamadalitellawi@gmail.com>
License:                                  Apache License
Classifier: License :: OSI Approved :: Apache Software License
Requires-Dist: forallpeople>=2.7.1
Requires-Dist: handcalcs>=1.9.0
Requires-Dist: matplotlib>=3.10.7
Requires-Dist: more-itertools>=10.8.0
Requires-Dist: numpy>=2.3.3
Requires-Dist: openpyxl>=3.1.5
Requires-Dist: pandas>=2.3.3
Requires-Dist: plotly>=6.3.1
Requires-Dist: pythonnet>=3.0.5
Requires-Dist: rich>=14.2.0
Requires-Dist: shapely>=2.1.2
Requires-Dist: xlwings>=0.33.16
Requires-Python: >=3.14
Project-URL: Home, https://github.com/mohamadalitellawi/Civil_Engineering_Tools/
